parse_ingredients/__init__.py
parse_ingredients/__version__.py
parse_ingredients-0.0.4.dist-info/LICENSE
parse_ingredients-0.0.4.dist-info/METADATA
parse_ingredients-0.0.4.dist-info/WHEEL
parse_ingredients-0.0.4.dist-info/top_level.txt
parse_ingredients-0.0.4.dist-info/RECORD
