Metadata-Version: 2.1
Name: parse-ingredients
Version: 0.0.4
Summary: Parse strings of ingredients to their name, unit, quantity and optional comments.
Home-page: https://github.com/MichielMag/parse-ingredients
Author: Michiel K
Author-email: 
License: UNKNOWN
Platform: UNKNOWN
Classifier: Programming Language :: Python :: 3
Classifier: License :: OSI Approved :: MIT License
Classifier: Operating System :: OS Independent
Requires-Python: >=3.6
License-File: LICENSE
